[{"id":1,"iv":1,"vs":[{"id":11,"iv":1},{"id":12,"iv":1},{"id":13,"iv":1},{"id":14,"iv":1},{"id":15,"iv":1}]},{"id":2,"iv":1,"vs":[{"id":21,"iv":1},{"id":22,"iv":1},{"id":23,"iv":1}]},{"id":3,"iv":1,"vs":[{"id":31,"iv":1},{"id":32,"iv":1},{"id":33,"iv":1},{"id":34,"iv":1},{"id":35,"iv":1},{"id":36,"iv":1}]},{"id":4,"iv":1,"vs":[{"id":41,"iv":1},{"id":42,"iv":1}]},{"id":5,"iv":1,"vs":[{"id":51,"iv":1},{"id":52,"iv":1}]},{"id":6,"iv":1,"vs":[{"id":61,"iv":1},{"id":62,"iv":1},{"id":63,"iv":1},{"id":64,"iv":1},{"id":65,"iv":1}]},{"id":7,"iv":1,"vs":[{"id":71,"iv":1},{"id":72,"iv":1},{"id":73,"iv":1}]},{"id":8,"iv":1,"vs":[{"id":81,"iv":1},{"id":82,"iv":1},{"id":83,"iv":1},{"id":84,"iv":1},{"id":85,"iv":1},{"id":86,"iv":1},{"id":87,"iv":1}]},{"id":9,"iv":0,"vs":[{"id":91,"iv":1},{"id":92,"iv":1}]},{"id":10,"iv":1,"vs":[{"id":101,"iv":1},{"id":102,"iv":1}]},{"id":11,"iv":0,"vs":[{"id":111,"iv":1},{"id":112,"iv":1}]},{"id":12,"iv":1,"vs":[{"id":121,"iv":1},{"id":122,"iv":1},{"id":123,"iv":1}]},{"id":13,"iv":1,"vs":[{"id":131,"iv":1},{"id":132,"iv":1},{"id":133,"iv":1}]},{"id":14,"iv":0,"vs":[{"id":141,"iv":1},{"id":142,"iv":1}]},{"id":15,"iv":0,"vs":[{"id":151,"iv":1},{"id":152,"iv":1}]},{"id":16,"iv":0,"vs":[{"id":161,"iv":1},{"id":162,"iv":1}]},{"id":17,"iv":1,"vs":[{"id":171,"iv":1},{"id":172,"iv":1},{"id":173,"iv":1}]},{"id":18,"iv":1,"vs":[{"id":181,"iv":1},{"id":182,"iv":1},{"id":183,"iv":1}]},{"id":19,"iv":0,"vs":[{"id":191,"iv":1},{"id":192,"iv":1}]},{"id":20,"iv":0,"vs":[{"id":201,"iv":1},{"id":202,"iv":1}]},{"id":21,"iv":0,"vs":[{"id":211,"iv":1},{"id":212,"iv":1}]},{"id":22,"iv":1,"vs":[{"id":221,"iv":1},{"id":222,"iv":1},{"id":223,"iv":1},{"id":224,"iv":1},{"id":225,"iv":1},{"id":226,"iv":1}]},{"id":23,"iv":1,"vs":[{"id":231,"iv":1},{"id":232,"iv":1}]},{"id":24,"iv":0,"vs":[{"id":241,"iv":1},{"id":242,"iv":1}]},{"id":25,"iv":1,"vs":[{"id":251,"iv":1},{"id":252,"iv":1},{"id":253,"iv":1},{"id":254,"iv":1}]},{"id":26,"iv":0,"vs":[{"id":261,"iv":1},{"id":262,"iv":1}]},{"id":27,"iv":0,"vs":[{"id":271,"iv":1},{"id":272,"iv":1}]},{"id":28,"iv":0,"vs":[{"id":281,"iv":1},{"id":282,"iv":1}]},{"id":29,"iv":1,"vs":[{"id":291,"iv":1},{"id":292,"iv":1}]},{"id":30,"iv":1,"vs":[{"id":301,"iv":1}]},{"id":31,"iv":1,"vs":[{"id":311,"iv":1},{"id":312,"iv":1},{"id":313,"iv":1}]},{"id":32,"iv":0,"vs":[{"id":321,"iv":1},{"id":322,"iv":1}]},{"id":33,"iv":1,"vs":[{"id":331,"iv":1}]},{"id":34,"iv":0,"vs":[{"id":341,"iv":1},{"id":342,"iv":1}]},{"id":35,"iv":0,"vs":[{"id":351,"iv":1},{"id":352,"iv":1}]},{"id":36,"iv":0,"vs":[{"id":361,"iv":1},{"id":362,"iv":1}]},{"id":37,"iv":0,"vs":[{"id":371,"iv":1},{"id":372,"iv":1}]},{"id":38,"iv":0,"vs":[{"id":381,"iv":1},{"id":382,"iv":1}]},{"id":39,"iv":0,"vs":[{"id":391,"iv":1},{"id":392,"iv":1}]},{"id":40,"iv":0,"vs":[{"id":401,"iv":1},{"id":402,"iv":1}]},{"id":41,"iv":1,"vs":[{"id":411,"iv":1},{"id":412,"iv":1},{"id":413,"iv":1},{"id":414,"iv":1}]}]